edir.py
edir-2.35.dist-info/METADATA
edir-2.35.dist-info/WHEEL
edir-2.35.dist-info/entry_points.txt
edir-2.35.dist-info/top_level.txt
edir-2.35.dist-info/RECORD
