Metadata-Version: 2.4
Name: edir
Version: 2.35
Summary: Utility to rename, remove, and copy files/dirs using your editor
Author-email: Mark Blakeney <mark.blakeney@bullet-systems.net>
License-Expression: GPL-3.0-or-later
Project-URL: Homepage, https://github.com/bulletmark/edir
Keywords: vidir,git,trash,trash-put,thrash-d
Classifier: Programming Language :: Python :: 3
Requires-Python: >=3.8
Requires-Dist: argparse-from-file
Requires-Dist: natsort
